{
 "_type": "album",
 "api_path": "/albums/42829",
 "cover_art_thumbnail_url": "https://images.genius.com/2869e2355d7882993598eac98345c45d.300x300x1.jpg",
 "cover_art_url": "https://images.genius.com/2869e2355d7882993598eac98345c45d.1000x1000x1.jpg",
 "full_title": "Tug of War by Paul McCartney",
 "id": 42829,
 "name": "Tug of War",
 "name_with_artist": "Tug of War (artist: Paul McCartney)",
 "release_date_components": {
  "year": 1982,
  "month": 4,
  "day": 26
 },
 "url": "https://genius.com/albums/Paul-mccartney/Tug-of-war",
 "artist": {
  "_type": "artist",
  "api_path": "/artists/1601",
  "header_image_url": "https://images.genius.com/b7037d68b09fd6a60ca4b8d62ef06637.1000x380x1.jpg",
  "id": 1601,
  "image_url": "https://images.genius.com/c59144581e94a6769362a9775a11d362.1000x1000x1.jpg",
  "index_character": "p",
  "is_meme_verified": true,
  "is_verified": true,
  "name": "Paul McCartney",
  "slug": "Paul-mccartney",
  "url": "https://genius.com/artists/Paul-mccartney",
  "iq": 1800
 },
 "songs": [
  {
   "_type": "song",
   "annotation_count": 2,
   "api_path": "/songs/387597",
   "full_title": "Tug of War by\u00a0Paul\u00a0McCartney",
   "header_image_thumbnail_url": "https://images.genius.com/f2897d05add9df83006c2d8ee201a3a0.300x300x1.jpg",
   "header_image_url": "https://images.genius.com/f2897d05add9df83006c2d8ee201a3a0.440x440x1.jpg",
   "id": 387597,
   "instrumental": false,
   "lyrics_owner_id": 354383,
   "lyrics_state": "complete",
   "lyrics_updated_at": 1602340952,
   "path": "/Paul-mccartney-tug-of-war-lyrics",
   "pyongs_count": null,
   "song_art_image_thumbnail_url": "https://images.genius.com/f2897d05add9df83006c2d8ee201a3a0.300x300x1.jpg",
   "song_art_image_url": "https://images.genius.com/f2897d05add9df83006c2d8ee201a3a0.440x440x1.jpg",
   "stats": {
    "unreviewed_annotations": 2,
    "hot": false
   },
   "title": "Tug of War",
   "title_with_featured": "Tug of War",
   "updated_by_human_at": 1602340952,
   "url": "https://genius.com/Paul-mccartney-tug-of-war-lyrics",
   "primary_artist": {
    "_type": "artist",
    "api_path": "/artists/1601",
    "header_image_url": "https://images.genius.com/b7037d68b09fd6a60ca4b8d62ef06637.1000x380x1.jpg",
    "id": 1601,
    "image_url": "https://images.genius.com/c59144581e94a6769362a9775a11d362.1000x1000x1.jpg",
    "index_character": "p",
    "is_meme_verified": true,
    "is_verified": true,
    "name": "Paul McCartney",
    "slug": "Paul-mccartney",
    "url": "https://genius.com/artists/Paul-mccartney",
    "iq": 1800
   },
   "artist": "Paul McCartney",
   "lyrics": "[Verse 1]\nIt's a tug of war\nWhat with one thing and another\nIt's a tug of war\nWe expected more\nBut with one thing and another\nWe were trying to outdo each other\nIn a tug of war\n\n[Bridge 1]\nIn another world\nIn another world we could\nStand on top of the mountain\nWith our flag unfurled\nIn a time to come\nIn a time to come we will be\nDancing to the beat played\nOn a different drum\n\n[Verse 2]\nIt's a tug of war\nThough I know I mustn't grumble\nIt's a tug of war\nBut I can't let go\nIf I do you'll take a tumble\nAnd the whole thing is going to crumble\nIt's a tug of war\n(Pushing and pushing, pulling and pulling\nPushing and pulling)\n\n[Bridge 2]\nIn years to come they may discover\nWhat the air we breathe and the life we lead\nAre all about\nBut it won't be soon enough\nSoon enough for me\nNo it won't be soon enough\nSoon enough for me\n\n[Bridge 1]\nIn another world we could\nStand on top of the mountain\nWith our flag unfurled\nIn a time to come we will be\nDancing to the beat played\nOn a different drum\nWe will be dancing to the beat\nPlayed on a different drum\nWe will be dancing to the beat\nPlayed on a different drum\n\n[Verse 3]\nIt's a tug of war\n(A tug of war, a tug of war)\nWhat with one thing and another\nIt's a tug of war\nWe expected more\nBut with one thing and another\nWe were trying to outscore each other\nIn a tug of war\n(Pushing and pushing\nPulling and pulling\nPushing and pulling)"
  },
  {
   "_type": "song",
   "annotation_count": 1,
   "api_path": "/songs/387602",
   "full_title": "Take It Away by\u00a0Paul\u00a0McCartney",
   "header_image_thumbnail_url": "https://images.genius.com/2bbb50cafe0f1cc1edccb23ac74b8b16.300x300x1.jpg",
   "header_image_url": "https://images.genius.com/2bbb50cafe0f1cc1edccb23ac74b8b16.1000x1000x1.jpg",
   "id": 387602,
   "instrumental": false,
   "lyrics_owner_id": 354383,
   "lyrics_state": "complete",
   "lyrics_updated_at": 1602341729,
   "path": "/Paul-mccartney-take-it-away-lyrics",
   "pyongs_count": 1,
   "song_art_image_thumbnail_url": "https://images.genius.com/a902e8a6eaabafbc23443975cf4b88c2.300x300x1.jpg",
   "song_art_image_url": "https://images.genius.com/a902e8a6eaabafbc23443975cf4b88c2.1000x1000x1.jpg",
   "stats": {
    "unreviewed_annotations": 0,
    "hot": false
   },
   "title": "Take It Away",
   "title_with_featured": "Take It Away",
   "updated_by_human_at": 1602341729,
   "url": "https://genius.com/Paul-mccartney-take-it-away-lyrics",
   "primary_artist": {
    "_type": "artist",
    "api_path": "/artists/1601",
    "header_image_url": "https://images.genius.com/b7037d68b09fd6a60ca4b8d62ef06637.1000x380x1.jpg",
    "id": 1601,
    "image_url": "https://images.genius.com/c59144581e94a6769362a9775a11d362.1000x1000x1.jpg",
    "index_character": "p",
    "is_meme_verified": true,
    "is_verified": true,
    "name": "Paul McCartney",
    "slug": "Paul-mccartney",
    "url": "https://genius.com/artists/Paul-mccartney",
    "iq": 1800
   },
   "artist": "Paul McCartney",
   "lyrics": "[Chorus]\nTake it away\nWant to hear you play\nTill the lights go down\nTake it away\nDon't you want to stay\nTill there's no one else around\n\nTake it away\nWant to hear you play\nTill the lights go down\nTake it away\nDon't you want to stay\nTill there's no one else around\n\n[Verse 1]\nLonely driver\nOut on the road\nWith a hundred miles to go\nSole survivor\nCarrying the load\nSwitches on his radio\n\n[Chorus]\nTake it away\nWant to hear you play\nTill the lights go down\nTake it away\nDon't you want to stay\nTill there's no one else around\nMmmm\n\nTake it away\nWant to hear you play\nTill the lights go down\nTake it away\nDon't you want to stay\nTill there's no one else around\n\n[Verse 2]\nIn the audience\nWatching the show\nWith a paper in his hand\n(In his hand, in his hand)\nSome important impresario\nHas a message for the band\nOh!\n\n[Chorus]\nTake it away\nWant to hear you play\nTill the lights go down\n(Down, down)\nTake it away\nDon't you want to stay\nTill there's no one else around\n\n[Bridge]\nYou never know who may be\nListening to you\n(Never know who may be listening to you)\n(You never know who may be listening to you)\nTake it away\nTake it away\n\n[Verse 3]\nAfter hours\nLate in the bar\nBy a darkened corner seat\nFaded flowers\nWade in the jar\nTill the evening is complete\n\n[Outro]\n(Hah!\nAh!\nAh!\nAh!)"
  },
  {
   "_type": "song",
   "annotation_count": 1,
   "api_path": "/songs/387604",
   "full_title": "Somebody Who Cares by\u00a0Paul\u00a0McCartney",
   "header_image_thumbnail_url": "https://images.genius.com/2ec7159f38a43ccd44fc5eb2fe8170db.300x300x1.jpg",
   "header_image_url": "https://images.genius.com/2ec7159f38a43ccd44fc5eb2fe8170db.440x440x1.jpg",
   "id": 387604,
   "instrumental": false,
   "lyrics_owner_id": 354383,
   "lyrics_state": "complete",
   "lyrics_updated_at": 1602343036,
   "path": "/Paul-mccartney-somebody-who-cares-lyrics",
   "pyongs_count": null,
   "song_art_image_thumbnail_url": "https://images.genius.com/2ec7159f38a43ccd44fc5eb2fe8170db.300x300x1.jpg",
   "song_art_image_url": "https://images.genius.com/2ec7159f38a43ccd44fc5eb2fe8170db.440x440x1.jpg",
   "stats": {
    "unreviewed_annotations": 0,
    "hot": false
   },
   "title": "Somebody Who Cares",
   "title_with_featured": "Somebody Who Cares",
   "updated_by_human_at": 1602343036,
   "url": "https://genius.com/Paul-mccartney-somebody-who-cares-lyrics",
   "primary_artist": {
    "_type": "artist",
    "api_path": "/artists/1601",
    "header_image_url": "https://images.genius.com/b7037d68b09fd6a60ca4b8d62ef06637.1000x380x1.jpg",
    "id": 1601,
    "image_url": "https://images.genius.com/c59144581e94a6769362a9775a11d362.1000x1000x1.jpg",
    "index_character": "p",
    "is_meme_verified": true,
    "is_verified": true,
    "name": "Paul McCartney",
    "slug": "Paul-mccartney",
    "url": "https://genius.com/artists/Paul-mccartney",
    "iq": 1800
   },
   "artist": "Paul McCartney",
   "lyrics": "[Verse 1]\nWhen your body is coming apart at the seams\nAnd the whole thing's feeling low\nYou're convincing yourself that there's nobody there, I know\nI know how you feel\n\n[Verse 2]\nLike somebody has taken the wheels off your car\nWhen you had somewhere to go\nWell it's annoying, not going to get very far, I know\nBut somebody cares\n\n[Chorus]\nThere's always someone, somewhere\nYou should know by now\nAlways somebody who cares\nIt's happening day in, day out\nWell you know by now\nAlways somebody who cares\n\n[Post-Chorus]\nAnd if you don't know it, how will it find you?\nHow will we know your whereabouts?\nBut I know how you feel\n\n[Interlude]\nI know how you feel\n\n[Verse 3]\nLike somebody has taken the wheels off your car\nWhen you had somewhere to go\nWell it's frustrating, not going to get very far, I know\nBut somebody cares\n\n[Chorus]\nThere's always someone, somewhere\nYou should know by now\nAlways somebody who cares\nIt's happening day in, day out\nWell you know by now\nAlways somebody who cares\n\n[Post-Chorus]\nAnd if you don't know it, how will it find you?\nHow will we know your whereabouts?\nBut I know how you feel"
  },
  {
   "_type": "song",
   "annotation_count": 1,
   "api_path": "/songs/387610",
   "full_title": "What's That You're Doing? by\u00a0Paul\u00a0McCartney (Ft.\u00a0Stevie\u00a0Wonder)",
   "header_image_thumbnail_url": "https://images.genius.com/2ec7159f38a43ccd44fc5eb2fe8170db.300x300x1.jpg",
   "header_image_url": "https://images.genius.com/2ec7159f38a43ccd44fc5eb2fe8170db.440x440x1.jpg",
   "id": 387610,
   "instrumental": false,
   "lyrics_owner_id": 354383,
   "lyrics_state": "complete",
   "lyrics_updated_at": 1602364340,
   "path": "/Paul-mccartney-whats-that-youre-doing-lyrics",
   "pyongs_count": null,
   "song_art_image_thumbnail_url": "https://images.genius.com/2ec7159f38a43ccd44fc5eb2fe8170db.300x300x1.jpg",
   "song_art_image_url": "https://images.genius.com/2ec7159f38a43ccd44fc5eb2fe8170db.440x440x1.jpg",
   "stats": {
    "unreviewed_annotations": 1,
    "hot": false
   },
   "title": "What\u2019s That You\u2019re Doing?",
   "title_with_featured": "What's That You're Doing? (Ft.\u00a0Stevie\u00a0Wonder)",
   "updated_by_human_at": 1602364340,
   "url": "https://genius.com/Paul-mccartney-whats-that-youre-doing-lyrics",
   "primary_artist": {
    "_type": "artist",
    "api_path": "/artists/1601",
    "header_image_url": "https://images.genius.com/b7037d68b09fd6a60ca4b8d62ef06637.1000x380x1.jpg",
    "id": 1601,
    "image_url": "https://images.genius.com/c59144581e94a6769362a9775a11d362.1000x1000x1.jpg",
    "index_character": "p",
    "is_meme_verified": true,
    "is_verified": true,
    "name": "Paul McCartney",
    "slug": "Paul-mccartney",
    "url": "https://genius.com/artists/Paul-mccartney",
    "iq": 1800
   },
   "artist": "Paul McCartney",
   "lyrics": "[Intro: Stevie Wonder]\nGood morning\nOr good afternoon?\nGood night\n\n[Verse 1: Stevie]\nWhat's that you're doing?\nGirl I like what you do to me\nWhat's that you're doing?\n'Cause it makes no kind of sense to me\nYou can make me feel so proud\nYou can make me holler ow!\nGirl you make me want to dance and sing\nMy mind is blown and you're to blame\nI say it's sunning when there's rain\nI jump by leaps and bounds, just call my name\n\n[Verse 2: Paul]\nWhat's that you're saying?\nGirl I likes the way you talk to me\nWhat's that you're saying?\nEven if it's wrong girl I do agree\n\nGirl you make me feel so small\nThough I might stand six feet tall\nWhat you've got cuts me right down to size\nI'll be the last, you'll be the first\nI'll do my best to quench your thirst\nI'm the lucky one who keeps the prize\n\n[Chorus 1: Stevie & Paul]\nGirl I like what you're doing\nBaby do it some more\nGirl I like what you're doing\nBaby do it some more\n'Cause I like what you\nDo to me, do to me\nDo it some more\nDo it to me, do it to me\nDo it some more\n\n[Ad lib: Stevie]\nDo you know that I'm appreciating\nWhat you do to me?\n\n[Verse 3: Stevie & Paul]\nWhat's that you're doing?\nGirl I like what you do to me, ooh\nWhat's that you're doing?\n'Cause it makes no kind of sense to me\n\nYou can fill my appetite\nWithout me taking up a bite\nNever knew that love could fill you up\nYou're much too good for me to pass\nI'm for the taking, you just ask\nWe can make it stick with love and luck\n\n[Chorus: Stevie & Paul]\nGirl, I like what you're doing\n(Girl, I like what you're doing)\nBaby do it some more\nGirl, I like what you're doing\n(Girl, I like what you're doing)\nBaby, do it some more\nDo it to me, do it to me\nDo it some more\nYou know I like what you're doing\nGirl, I like what you're doing\nBaby, do it some more\n\n[Instrumental interlude with synth solo]\nWhat's that you're doing?\n\n[Verse 4: Stevie & Paul]\nWhat's that I'm feeling?\nThat sensation's such a mystery\nI know that it's thrilling\nAnd I hope this feeling lasts eternally\n\nGirl, you make me scream and shout\nTell me what it's all about\nYou make me give in without a fight\nI don't have no words to say\nYou can fill it anyway\nAnd everything you do will turn out right\n\n[Chorus: Stevie & Paul]\nGirl, I like what you're doing\nCome on baby, do it some more\nGirl, I like what you're doing\nBaby do it some more\n\nWe love you yeah yeah yeah\nWe love you yeah yeah yeah yeah\nBaby, do it some more\n\nGirl, I like what you're doing\nWhen it's one o'clock, when it's two o'clock\nWhen three, when four, when five o'clock\nWhen it's seven o'clock, when it's eight o'clock\nNine and ten and eleven o'clock\nWhen it's one o'clock, when it's two o'clock\n\nGirl, I like what you're doing"
  },
  {
   "_type": "song",
   "annotation_count": 10,
   "api_path": "/songs/207023",
   "full_title": "Here Today by\u00a0Paul\u00a0McCartney",
   "header_image_thumbnail_url": "https://images.genius.com/2869e2355d7882993598eac98345c45d.300x300x1.jpg",
   "header_image_url": "https://images.genius.com/2869e2355d7882993598eac98345c45d.1000x1000x1.jpg",
   "id": 207023,
   "instrumental": false,
   "lyrics_owner_id": 271314,
   "lyrics_state": "complete",
   "lyrics_updated_at": 1602370941,
   "path": "/Paul-mccartney-here-today-lyrics",
   "pyongs_count": 4,
   "song_art_image_thumbnail_url": "https://images.genius.com/2869e2355d7882993598eac98345c45d.300x300x1.jpg",
   "song_art_image_url": "https://images.genius.com/2869e2355d7882993598eac98345c45d.1000x1000x1.jpg",
   "stats": {
    "unreviewed_annotations": 4,
    "hot": false,
    "pageviews": 22943
   },
   "title": "Here Today",
   "title_with_featured": "Here Today",
   "updated_by_human_at": 1606196079,
   "url": "https://genius.com/Paul-mccartney-here-today-lyrics",
   "primary_artist": {
    "_type": "artist",
    "api_path": "/artists/1601",
    "header_image_url": "https://images.genius.com/b7037d68b09fd6a60ca4b8d62ef06637.1000x380x1.jpg",
    "id": 1601,
    "image_url": "https://images.genius.com/c59144581e94a6769362a9775a11d362.1000x1000x1.jpg",
    "index_character": "p",
    "is_meme_verified": true,
    "is_verified": true,
    "name": "Paul McCartney",
    "slug": "Paul-mccartney",
    "url": "https://genius.com/artists/Paul-mccartney",
    "iq": 1800
   },
   "artist": "Paul McCartney",
   "lyrics": "[Verse 1]\nAnd if I said I really knew you well\nWhat would your answer be\nIf you were here today?\nOoh ooh ooh, here today\n\n[Verse 2]\nWell, knowing you\nYou'd probably laugh and say that we were worlds apart\nIf you were here today\nOoh, ooh, ooh, here today\n\n[Bridge 1]\nBut as for me, I still remember how it was before\nAnd I am holding back the tears no more\nOoh, ooh, ooh\nI love you\nOoh, ooh\n\n[Bridge 2]\nWhat about the time we met? (What about the time we met?)\nWell, I suppose that you could say that we were playing hard to get\nDidn't understand a thing, but we could always sing\nWhat about the night we cried? (What about the night we cried?)\nBecause there wasn't any reason left to keep it all inside\nNever understood a word, but you were always there with a smile\n\n[Verse 3]\nAnd if I say I really loved you and was glad you came along\nWhen you were here today\nOoh, ooh, ooh, for you were in my song\nOoh ooh ooh, here today"
  },
  {
   "_type": "song",
   "annotation_count": 1,
   "api_path": "/songs/387620",
   "full_title": "Ballroom Dancing by\u00a0Paul\u00a0McCartney",
   "header_image_thumbnail_url": "https://images.genius.com/2ec7159f38a43ccd44fc5eb2fe8170db.300x300x1.jpg",
   "header_image_url": "https://images.genius.com/2ec7159f38a43ccd44fc5eb2fe8170db.440x440x1.jpg",
   "id": 387620,
   "instrumental": false,
   "lyrics_owner_id": 354383,
   "lyrics_state": "complete",
   "lyrics_updated_at": 1598325651,
   "path": "/Paul-mccartney-ballroom-dancing-lyrics",
   "pyongs_count": null,
   "song_art_image_thumbnail_url": "https://images.genius.com/2ec7159f38a43ccd44fc5eb2fe8170db.300x300x1.jpg",
   "song_art_image_url": "https://images.genius.com/2ec7159f38a43ccd44fc5eb2fe8170db.440x440x1.jpg",
   "stats": {
    "unreviewed_annotations": 0,
    "hot": false
   },
   "title": "Ballroom Dancing",
   "title_with_featured": "Ballroom Dancing",
   "updated_by_human_at": 1598325651,
   "url": "https://genius.com/Paul-mccartney-ballroom-dancing-lyrics",
   "primary_artist": {
    "_type": "artist",
    "api_path": "/artists/1601",
    "header_image_url": "https://images.genius.com/b7037d68b09fd6a60ca4b8d62ef06637.1000x380x1.jpg",
    "id": 1601,
    "image_url": "https://images.genius.com/c59144581e94a6769362a9775a11d362.1000x1000x1.jpg",
    "index_character": "p",
    "is_meme_verified": true,
    "is_verified": true,
    "name": "Paul McCartney",
    "slug": "Paul-mccartney",
    "url": "https://genius.com/artists/Paul-mccartney",
    "iq": 1800
   },
   "artist": "Paul McCartney",
   "lyrics": "[Verse 1]\nWell I used to smile when I was a pup\nSailing down the Nile in a china cup\nWith the recipe for a lovely day\nSticking out of my back pocket\n\n[Pre-Chorus]\nBut it wasn't always such a pretty sight\n'Cause we used to fight like cats and dogs\nTill we made it up in the ballroom\n\n[Chorus 1]\nBallroom dancing made a man of me\nOne, two, three, four\nI just plain adore your ballroom dancing\nSeen it on TV\nI got what I got from ballroom dancing\nBig B.D\n\n[Verse 2]\nWell I used to fly when I was a kid\nAnd I didn't cry if it hurt a bit\nOn a carpet ride to a foreign land\nAt the time of Davy Crockett\n\n[Pre-Chorus]\nBut it wasn't always such a pretty sight\n'Cause we used to fight like cats and dogs\nTill we made it up in the ballroom\n\n[Chorus 2]\nBallroom dancing made a man of me\nOne, two, three, four\nI just plain adore your\nBallroom dancing, seen it on TV\nI got quite a lot from ballroom dancing\nBig B.D\n\n[Verse 3]\nWell it went so fast and we all grew up\nNow the days that passed in the china cup\nAre the memories of another day\nAnd I wouldn't want to knock it\n\n[Pre-Chorus]\nBut it wasn't always such a pretty sight\n'Cause we used to fight like cats and dogs\nTill we made it up in the ballroom\n\n[Chorus 2]\nBallroom dancing made a man of me\nOne, two, three, four\nI just plain adore your\nBallroom dancing, seen it on TV\nI got quite a lot from ballroom dancing\nBig B.D\nOh!"
  },
  {
   "_type": "song",
   "annotation_count": 0,
   "api_path": "/songs/387621",
   "full_title": "The Pound is Sinking by\u00a0Paul\u00a0McCartney",
   "header_image_thumbnail_url": "https://images.genius.com/2ec7159f38a43ccd44fc5eb2fe8170db.300x300x1.jpg",
   "header_image_url": "https://images.genius.com/2ec7159f38a43ccd44fc5eb2fe8170db.440x440x1.jpg",
   "id": 387621,
   "instrumental": false,
   "lyrics_owner_id": 354383,
   "lyrics_state": "complete",
   "lyrics_updated_at": 1602370497,
   "path": "/Paul-mccartney-the-pound-is-sinking-lyrics",
   "pyongs_count": null,
   "song_art_image_thumbnail_url": "https://images.genius.com/2ec7159f38a43ccd44fc5eb2fe8170db.300x300x1.jpg",
   "song_art_image_url": "https://images.genius.com/2ec7159f38a43ccd44fc5eb2fe8170db.440x440x1.jpg",
   "stats": {
    "unreviewed_annotations": 0,
    "hot": false
   },
   "title": "The Pound is Sinking",
   "title_with_featured": "The Pound is Sinking",
   "updated_by_human_at": 1602370497,
   "url": "https://genius.com/Paul-mccartney-the-pound-is-sinking-lyrics",
   "primary_artist": {
    "_type": "artist",
    "api_path": "/artists/1601",
    "header_image_url": "https://images.genius.com/b7037d68b09fd6a60ca4b8d62ef06637.1000x380x1.jpg",
    "id": 1601,
    "image_url": "https://images.genius.com/c59144581e94a6769362a9775a11d362.1000x1000x1.jpg",
    "index_character": "p",
    "is_meme_verified": true,
    "is_verified": true,
    "name": "Paul McCartney",
    "slug": "Paul-mccartney",
    "url": "https://genius.com/artists/Paul-mccartney",
    "iq": 1800
   },
   "artist": "Paul McCartney",
   "lyrics": "[Intro]\nThe pound is sinking, the peso's falling\nThe lira's reeling and feeling quite appalling\n\n[Verse 1]\nThe mark is holding, the franc is fading\nThe drachma's very weak, but everyone's still trading\nThe market's bottom has fallen right out\nAnd only the strong are survivors\n\n[Bridge 1]\nWell, I fear, my dear, that it's eminently clear\nThat you can't see the trees for the forest\nYour father was an extraordinary man\nBut you don't seem to have inherited many of his mannerisms\nOh, any of his mannerisms\n\n[Verse 2]\nThe dollar's moving, the ruble's rising\nThe yen is keeping up, which hardly seems surprising\nThe market's bottom has fallen right out\nAnd only the stout are survivors\n\n[Bridge 2]\nHear me, my lover (Hear me lover)\nI can't be held responsible now (Oh no, it wasn't me)\nFor something that didn't happen (I didn't do it anyway)\nI knew you for a minute\nOh, it didn't happen only for a minute\nYour heart just wasn't in it anymore\nMmm, hmm\n\n[Outro]\nThe pound is sinking, the peso's falling\nThe lira's reeling and feeling quite appalling"
  },
  {
   "_type": "song",
   "annotation_count": 1,
   "api_path": "/songs/387629",
   "full_title": "Wanderlust by\u00a0Paul\u00a0McCartney",
   "header_image_thumbnail_url": "https://images.genius.com/2ec7159f38a43ccd44fc5eb2fe8170db.300x300x1.jpg",
   "header_image_url": "https://images.genius.com/2ec7159f38a43ccd44fc5eb2fe8170db.440x440x1.jpg",
   "id": 387629,
   "instrumental": false,
   "lyrics_owner_id": 354383,
   "lyrics_state": "complete",
   "lyrics_updated_at": 1602371844,
   "path": "/Paul-mccartney-wanderlust-lyrics",
   "pyongs_count": null,
   "song_art_image_thumbnail_url": "https://images.genius.com/2ec7159f38a43ccd44fc5eb2fe8170db.300x300x1.jpg",
   "song_art_image_url": "https://images.genius.com/2ec7159f38a43ccd44fc5eb2fe8170db.440x440x1.jpg",
   "stats": {
    "unreviewed_annotations": 1,
    "hot": false
   },
   "title": "Wanderlust",
   "title_with_featured": "Wanderlust",
   "updated_by_human_at": 1602371844,
   "url": "https://genius.com/Paul-mccartney-wanderlust-lyrics",
   "primary_artist": {
    "_type": "artist",
    "api_path": "/artists/1601",
    "header_image_url": "https://images.genius.com/b7037d68b09fd6a60ca4b8d62ef06637.1000x380x1.jpg",
    "id": 1601,
    "image_url": "https://images.genius.com/c59144581e94a6769362a9775a11d362.1000x1000x1.jpg",
    "index_character": "p",
    "is_meme_verified": true,
    "is_verified": true,
    "name": "Paul McCartney",
    "slug": "Paul-mccartney",
    "url": "https://genius.com/artists/Paul-mccartney",
    "iq": 1800
   },
   "artist": "Paul McCartney",
   "lyrics": "[Verse 1]\nLight out wanderlust\nHead us out to sea\nCaptain says there'll be a bust\nThis one's not for me\n\nTake us from the dark\nOut where we can see\nCaptain's out to make his mark\nThis one's not to be\n\n[Chorus]\nLight out wanderlust\nHelp us to be free\nLight out wanderlust\nDo it just for me\nWanderlust\n\n[Verse 2]\nOh where did I go wrong, my love?\nWhat petty crime was I found guilty of?\nWhat better time to find a brand new day?\nOh - wanderlust away\n\n[Chorus]\nLight out wanderlust\nHelp us to be free\nLight out wanderlust\nDo it just for me\nWanderlust\n\n[Verse 3]\nCaptain's out to make his mark\nThis one's not to be\n\n[Verse 1/Verse 2 countermelody]\nLight out wanderlust\n(Oh where did I go wrong, my love?)\nHead us out to sea\n(What petty crime was I found guilty of?)\nCaptain says there'll be a bust\n(What better time to find a brand new day?)\nThis one's not for me\n(Oh - wanderlust away)\n\n[Outro]\nDropping a line\nMaybe this time\nIt's wanderlust for me"
  },
  {
   "_type": "song",
   "annotation_count": 1,
   "api_path": "/songs/387632",
   "full_title": "Get It by\u00a0Paul\u00a0McCartney (Ft.\u00a0Carl\u00a0Perkins)",
   "header_image_thumbnail_url": "https://images.genius.com/2ec7159f38a43ccd44fc5eb2fe8170db.300x300x1.jpg",
   "header_image_url": "https://images.genius.com/2ec7159f38a43ccd44fc5eb2fe8170db.440x440x1.jpg",
   "id": 387632,
   "instrumental": false,
   "lyrics_owner_id": 354383,
   "lyrics_state": "complete",
   "lyrics_updated_at": 1602372638,
   "path": "/Paul-mccartney-get-it-lyrics",
   "pyongs_count": null,
   "song_art_image_thumbnail_url": "https://images.genius.com/2ec7159f38a43ccd44fc5eb2fe8170db.300x300x1.jpg",
   "song_art_image_url": "https://images.genius.com/2ec7159f38a43ccd44fc5eb2fe8170db.440x440x1.jpg",
   "stats": {
    "unreviewed_annotations": 0,
    "hot": false
   },
   "title": "Get It",
   "title_with_featured": "Get It (Ft.\u00a0Carl\u00a0Perkins)",
   "updated_by_human_at": 1602372638,
   "url": "https://genius.com/Paul-mccartney-get-it-lyrics",
   "primary_artist": {
    "_type": "artist",
    "api_path": "/artists/1601",
    "header_image_url": "https://images.genius.com/b7037d68b09fd6a60ca4b8d62ef06637.1000x380x1.jpg",
    "id": 1601,
    "image_url": "https://images.genius.com/c59144581e94a6769362a9775a11d362.1000x1000x1.jpg",
    "index_character": "p",
    "is_meme_verified": true,
    "is_verified": true,
    "name": "Paul McCartney",
    "slug": "Paul-mccartney",
    "url": "https://genius.com/artists/Paul-mccartney",
    "iq": 1800
   },
   "artist": "Paul McCartney",
   "lyrics": "[Chorus: Paul]\nYou've got to get it mm mm\nYou've got to get it don't forget\nIt doesn't come around again\nYou've got to get it mm mm\nYou've got to get it and you've got to get it good\n\n[Verse 1: Carl & Paul]\nOnce I had a little Spanish guitar\nThe neighbours told me I could go pretty far\nWell I came and I went\nAnd my guitar got bent\nBut I discovered that the people who love\nAre what we need if we're to get up above it all\nAnd that's that\nUnless the world is flat\n\n[Chorus: Carl & Paul]\nI want to get it mm mm\nI want to get it just in case\nIt doesn't come around again\nI want to get it mm mm\nI want to get it and I wanna get it good\n\n[Verse 2: Carl & Paul]\nPardon me if I've been misunderstood\nI want to get it while the going is good\nThe telephone rang\nAbout a song I sang\nThe life of Cadillac and ultra for sure\nIs automatic for a lady demure\nShe came and she went\nWithout a single dent\n\n[Chorus: Carl & Paul]\nYou've got to get it mm mm\nYou've got to get it don't forget\nIt doesn't come around again\nYou've got to get it mm mm\nYou've got to get it and you've got to get it good\n\n(I get you\nGo get)\n\n[Chorus: Carl & Paul]\nCome on, let's get it mm mm\nCome on, let's get it don't forget\nIt doesn't come around again\nYou've got to get it mm mm\nYou've got to get it and you've got to get it good"
  },
  {
   "_type": "song",
   "annotation_count": 1,
   "api_path": "/songs/387634",
   "full_title": "Be What You See (Link) by\u00a0Paul\u00a0McCartney",
   "header_image_thumbnail_url": "https://images.genius.com/2ec7159f38a43ccd44fc5eb2fe8170db.300x300x1.jpg",
   "header_image_url": "https://images.genius.com/2ec7159f38a43ccd44fc5eb2fe8170db.440x440x1.jpg",
   "id": 387634,
   "instrumental": false,
   "lyrics_owner_id": 354383,
   "lyrics_state": "complete",
   "lyrics_updated_at": 1504589243,
   "path": "/Paul-mccartney-be-what-you-see-link-lyrics",
   "pyongs_count": null,
   "song_art_image_thumbnail_url": "https://images.genius.com/2ec7159f38a43ccd44fc5eb2fe8170db.300x300x1.jpg",
   "song_art_image_url": "https://images.genius.com/2ec7159f38a43ccd44fc5eb2fe8170db.440x440x1.jpg",
   "stats": {
    "unreviewed_annotations": 0,
    "hot": false
   },
   "title": "Be What You See (Link)",
   "title_with_featured": "Be What You See (Link)",
   "updated_by_human_at": 1596016283,
   "url": "https://genius.com/Paul-mccartney-be-what-you-see-link-lyrics",
   "primary_artist": {
    "_type": "artist",
    "api_path": "/artists/1601",
    "header_image_url": "https://images.genius.com/b7037d68b09fd6a60ca4b8d62ef06637.1000x380x1.jpg",
    "id": 1601,
    "image_url": "https://images.genius.com/c59144581e94a6769362a9775a11d362.1000x1000x1.jpg",
    "index_character": "p",
    "is_meme_verified": true,
    "is_verified": true,
    "name": "Paul McCartney",
    "slug": "Paul-mccartney",
    "url": "https://genius.com/artists/Paul-mccartney",
    "iq": 1800
   },
   "artist": "Paul McCartney",
   "lyrics": "[Chorus]\nThe one you wanted to be\nIs now the one you see\nThe one you wanted to be\nIs now the one you see"
  },
  {
   "_type": "song",
   "annotation_count": 1,
   "api_path": "/songs/387644",
   "full_title": "Dress Me Up As A Robber by\u00a0Paul\u00a0McCartney",
   "header_image_thumbnail_url": "https://images.genius.com/2ec7159f38a43ccd44fc5eb2fe8170db.300x300x1.jpg",
   "header_image_url": "https://images.genius.com/2ec7159f38a43ccd44fc5eb2fe8170db.440x440x1.jpg",
   "id": 387644,
   "instrumental": false,
   "lyrics_owner_id": 354383,
   "lyrics_state": "complete",
   "lyrics_updated_at": 1457148050,
   "path": "/Paul-mccartney-dress-me-up-as-a-robber-lyrics",
   "pyongs_count": null,
   "song_art_image_thumbnail_url": "https://images.genius.com/2ec7159f38a43ccd44fc5eb2fe8170db.300x300x1.jpg",
   "song_art_image_url": "https://images.genius.com/2ec7159f38a43ccd44fc5eb2fe8170db.440x440x1.jpg",
   "stats": {
    "unreviewed_annotations": 0,
    "hot": false
   },
   "title": "Dress Me Up As A Robber",
   "title_with_featured": "Dress Me Up As A Robber",
   "updated_by_human_at": 1602383082,
   "url": "https://genius.com/Paul-mccartney-dress-me-up-as-a-robber-lyrics",
   "primary_artist": {
    "_type": "artist",
    "api_path": "/artists/1601",
    "header_image_url": "https://images.genius.com/b7037d68b09fd6a60ca4b8d62ef06637.1000x380x1.jpg",
    "id": 1601,
    "image_url": "https://images.genius.com/c59144581e94a6769362a9775a11d362.1000x1000x1.jpg",
    "index_character": "p",
    "is_meme_verified": true,
    "is_verified": true,
    "name": "Paul McCartney",
    "slug": "Paul-mccartney",
    "url": "https://genius.com/artists/Paul-mccartney",
    "iq": 1800
   },
   "artist": "Paul McCartney",
   "lyrics": "[Verse 1]\nYou can dress me up as a robber\nBut I won't be in disguise\nOnly love is a robber\nAnd he lives within your eyes\nOoh, ooh eee ooh\n\nYou can dress me up as a sailor\nBut I'll never run to sea\nAs long as your love is available to me\nWhat do I do with a sea of blue?\nOoh, eee ooh\n\n[Chorus]\nDressing me up\nIt doesn't make a difference\nWhat you want to do\nWhichever way you look at it\nI'm still in love with you\nIf we go on forever\nI may never make a change\n\nDressing me up\nAnd if I don't convince you\nYou needn't look too far\nTo see that I'm not lying\n'Cause I love you the way you are\nAnd what's the point of changing\nWhen I'm happy as I am?\n\n[Verse 2]\nWell you can dress me up as a soldier\nBut I wouldn't know what for\nI was the one that told you he loved you\nDon't want to go to another war\nNo, no, no"
  },
  {
   "_type": "song",
   "annotation_count": 2,
   "api_path": "/songs/387647",
   "full_title": "Ebony and Ivory by\u00a0Paul\u00a0McCartney (Ft.\u00a0Stevie\u00a0Wonder)",
   "header_image_thumbnail_url": "https://images.genius.com/218d9eec8e790a6c07527be6ec8d4b14.300x300x1.jpg",
   "header_image_url": "https://images.genius.com/218d9eec8e790a6c07527be6ec8d4b14.440x440x1.jpg",
   "id": 387647,
   "instrumental": false,
   "lyrics_owner_id": 354383,
   "lyrics_state": "complete",
   "lyrics_updated_at": 1603527972,
   "path": "/Paul-mccartney-ebony-and-ivory-lyrics",
   "pyongs_count": null,
   "song_art_image_thumbnail_url": "https://images.genius.com/a682c1498ebc4c9e9a1db40ec509f4d2.300x300x1.jpg",
   "song_art_image_url": "https://images.genius.com/a682c1498ebc4c9e9a1db40ec509f4d2.1000x1000x1.jpg",
   "stats": {
    "unreviewed_annotations": 1,
    "hot": false,
    "pageviews": 19777
   },
   "title": "Ebony and Ivory",
   "title_with_featured": "Ebony and Ivory (Ft.\u00a0Stevie\u00a0Wonder)",
   "updated_by_human_at": 1603527972,
   "url": "https://genius.com/Paul-mccartney-ebony-and-ivory-lyrics",
   "primary_artist": {
    "_type": "artist",
    "api_path": "/artists/1601",
    "header_image_url": "https://images.genius.com/b7037d68b09fd6a60ca4b8d62ef06637.1000x380x1.jpg",
    "id": 1601,
    "image_url": "https://images.genius.com/c59144581e94a6769362a9775a11d362.1000x1000x1.jpg",
    "index_character": "p",
    "is_meme_verified": true,
    "is_verified": true,
    "name": "Paul McCartney",
    "slug": "Paul-mccartney",
    "url": "https://genius.com/artists/Paul-mccartney",
    "iq": 1800
   },
   "artist": "Paul McCartney",
   "lyrics": "[Chorus]\nEbony and ivory\nLive together in perfect harmony\nSide by side on my piano keyboard\nOh Lord, why don't we?\n\n[Verse]\nWe all know that people are the same where ever you go\nThere is good and bad in everyone\nAnd we learn to live, we learn to give each other\nWhat we need to survive together alive\n\n[Chorus]\nEbony and ivory\nLive together in perfect harmony\nSide by side on my piano keyboard\nOh Lord, why don't we?\n\n[Bridge]\nEbony, ivory\nLiving in perfect harmony\nEbony, ivory, ooh\n\n[Verse]\nWe all know that people are the same where ever you go\nThere is good and bad in everyone\nWe learn to live when we learn to give each other\nWhat we need to survive together alive\n\n[Chorus]\nEbony and ivory\nLive together in perfect harmony\nSide by side on my piano keyboard\nOh Lord, why don't we?\nSide by side on my piano keyboard\nOh Lord, why don't we?\n\n[Outro]\nEbony, ivory\nLiving in perfect harmony\nEbony, ivory\nLiving in perfect harmony\nEbony, ivory\nLiving in perfect harmony\nEbony, ivory\nLiving in perfect harmony\nEbony, ivory\nLiving in perfect harmony\nEbony, ivory\nLiving in perfect harmony"
  },
  {
   "_type": "song",
   "annotation_count": 0,
   "api_path": "/songs/4208076",
   "full_title": "I\u2019ll Give You a Ring by\u00a0Paul\u00a0McCartney",
   "header_image_thumbnail_url": "https://images.genius.com/2869e2355d7882993598eac98345c45d.300x300x1.jpg",
   "header_image_url": "https://images.genius.com/2869e2355d7882993598eac98345c45d.1000x1000x1.jpg",
   "id": 4208076,
   "instrumental": false,
   "lyrics_owner_id": 2670856,
   "lyrics_state": "complete",
   "lyrics_updated_at": 1564714489,
   "path": "/Paul-mccartney-ill-give-you-a-ring-lyrics",
   "pyongs_count": null,
   "song_art_image_thumbnail_url": "https://images.genius.com/2869e2355d7882993598eac98345c45d.300x300x1.jpg",
   "song_art_image_url": "https://images.genius.com/2869e2355d7882993598eac98345c45d.1000x1000x1.jpg",
   "stats": {
    "unreviewed_annotations": 0,
    "hot": false
   },
   "title": "I\u2019ll Give You a Ring",
   "title_with_featured": "I\u2019ll Give You a Ring",
   "updated_by_human_at": 1596016347,
   "url": "https://genius.com/Paul-mccartney-ill-give-you-a-ring-lyrics",
   "primary_artist": {
    "_type": "artist",
    "api_path": "/artists/1601",
    "header_image_url": "https://images.genius.com/b7037d68b09fd6a60ca4b8d62ef06637.1000x380x1.jpg",
    "id": 1601,
    "image_url": "https://images.genius.com/c59144581e94a6769362a9775a11d362.1000x1000x1.jpg",
    "index_character": "p",
    "is_meme_verified": true,
    "is_verified": true,
    "name": "Paul McCartney",
    "slug": "Paul-mccartney",
    "url": "https://genius.com/artists/Paul-mccartney",
    "iq": 1800
   },
   "artist": "Paul McCartney",
   "lyrics": "[Verse 1]\nYou look a little lonely\nMaybe I could meet you\nTell me where to reach you\nAnd I'll give you a ring\n\n[Pre-Chorus 1]\nI'll take you to the pictures\nI'll miss the second feature\n\n[Chorus]\nLord, I can't believe my eyes, I must be dreaming\nGive me your number, I'll give you a ring\n\n[Verse 2]\nYou look a little hungry\nMaybe I could take you\nTell me when to wake you\nAnd I'll give you a ring\n\n[Pre-Chorus 2]\nI take you to the restaurant\nWe're looking at the menu\n\n[Chorus]\nLord, I can't believe my eyes, I must be dreaming\nGive me your number, I'll give you a ring\n\n[Bridge]\nOh man, I know I won't be lonely anymore (lonely anymore)\nMe and my phone, I'm gonna call your home\nI won't be lonely any more (lonely anymore)\n\n[Verse 1]\nYou look a little lonely\nMaybe I could meet you\nTell me where to reach you\nAnd I'll give you a ring\n\n[Pre-Chorus 1]\nI'll take you to the pictures\nMiss the second feature\n\n[Chorus]\nLord, I can't believe my eyes, I must be dreaming\nGive me your number, I'll give you a ring\nGive me your number, I'll give you a ring\n\n[Bridge]\nOh man, I know I won't be lonely anymore (lonely anymore)\nMe and my phone, I'm gonna call your home\nI won't be lonely any more (lonely anymore)\n\n[Verse 3]\nYou look a little sleepy\nWanna go to bed, dear?\nTell me can wed, dear\nI'll give you a ring\n\n[Pre-Chorus 3]\nTake you to the chapel\nListen to the sermon\n\n[Chorus]\nLord, I can't believe my ears, I must be dreaming\nGive me your number, I'll give you a ring\n\n[Outro]\nGive me your number, I'll give you a ring\nGive me your number, I'll give you a ring"
  },
  {
   "_type": "song",
   "annotation_count": 0,
   "api_path": "/songs/4745220",
   "full_title": "Rainclouds by\u00a0Paul\u00a0McCartney",
   "header_image_thumbnail_url": "https://images.genius.com/2869e2355d7882993598eac98345c45d.300x300x1.jpg",
   "header_image_url": "https://images.genius.com/2869e2355d7882993598eac98345c45d.1000x1000x1.jpg",
   "id": 4745220,
   "instrumental": false,
   "lyrics_owner_id": 6074356,
   "lyrics_state": "complete",
   "lyrics_updated_at": 1564711841,
   "path": "/Paul-mccartney-rainclouds-lyrics",
   "pyongs_count": null,
   "song_art_image_thumbnail_url": "https://images.genius.com/2869e2355d7882993598eac98345c45d.300x300x1.jpg",
   "song_art_image_url": "https://images.genius.com/2869e2355d7882993598eac98345c45d.1000x1000x1.jpg",
   "stats": {
    "unreviewed_annotations": 0,
    "hot": false
   },
   "title": "Rainclouds",
   "title_with_featured": "Rainclouds",
   "updated_by_human_at": 1596016322,
   "url": "https://genius.com/Paul-mccartney-rainclouds-lyrics",
   "primary_artist": {
    "_type": "artist",
    "api_path": "/artists/1601",
    "header_image_url": "https://images.genius.com/b7037d68b09fd6a60ca4b8d62ef06637.1000x380x1.jpg",
    "id": 1601,
    "image_url": "https://images.genius.com/c59144581e94a6769362a9775a11d362.1000x1000x1.jpg",
    "index_character": "p",
    "is_meme_verified": true,
    "is_verified": true,
    "name": "Paul McCartney",
    "slug": "Paul-mccartney",
    "url": "https://genius.com/artists/Paul-mccartney",
    "iq": 1800
   },
   "artist": "Paul McCartney",
   "lyrics": "Rain in the forest\nRain on the trees\nRaining down on me\nRainclouds hide the sun\nRainclouds hide the sun\n\nClouds in the valley\nClouds in the sky\nClouds, please\u201a pass me by\n\nSail the ocean\u201a sail across the sea (sail across the sea)\nSend a card to me (send a card to me)\nWind's gonna blow (wind's gonna blow)\nAnd if you go (o-o-o-o-o-oh)\nLeave the sun for me (me-ee-ee)\n\nTalkin' 'bout sun in the desert (sun in the desert)\nSun in my ears (sun in my ears)\nSun dries up my tears\nRainclouds hide the sun (rainclouds hide the sun)\nRainclouds hide the sun (rainclouds hide the sun)\n\nRain in the forest (rain in the forest)\nRain on the trees (rain on the trees)\nRaining down on me\nRainclouds hide the sun\u201a pretty woman, in the morning\n(rainclouds hide the sun)\nRainclouds hide the sun (rainclouds hide the sun)\n\nRain in the forest (rainclouds hide the sun)\nRain on the trees (rainclouds hide the sun)\nRainclouds hide the sun"
  },
  {
   "_type": "song",
   "annotation_count": 3,
   "api_path": "/songs/3603",
   "full_title": "Ebony and Ivory (Solo) by\u00a0Paul\u00a0McCartney",
   "header_image_thumbnail_url": "https://images.genius.com/2869e2355d7882993598eac98345c45d.300x300x1.jpg",
   "header_image_url": "https://images.genius.com/2869e2355d7882993598eac98345c45d.1000x1000x1.jpg",
   "id": 3603,
   "instrumental": false,
   "lyrics_owner_id": 7,
   "lyrics_state": "complete",
   "lyrics_updated_at": 1542523812,
   "path": "/Paul-mccartney-ebony-and-ivory-solo-annotated",
   "pyongs_count": null,
   "song_art_image_thumbnail_url": "https://images.genius.com/2869e2355d7882993598eac98345c45d.300x300x1.jpg",
   "song_art_image_url": "https://images.genius.com/2869e2355d7882993598eac98345c45d.1000x1000x1.jpg",
   "stats": {
    "unreviewed_annotations": 0,
    "hot": false
   },
   "title": "Ebony and Ivory (Solo)",
   "title_with_featured": "Ebony and Ivory (Solo)",
   "updated_by_human_at": 1551532923,
   "url": "https://genius.com/Paul-mccartney-ebony-and-ivory-solo-annotated",
   "primary_artist": {
    "_type": "artist",
    "api_path": "/artists/1601",
    "header_image_url": "https://images.genius.com/b7037d68b09fd6a60ca4b8d62ef06637.1000x380x1.jpg",
    "id": 1601,
    "image_url": "https://images.genius.com/c59144581e94a6769362a9775a11d362.1000x1000x1.jpg",
    "index_character": "p",
    "is_meme_verified": true,
    "is_verified": true,
    "name": "Paul McCartney",
    "slug": "Paul-mccartney",
    "url": "https://genius.com/artists/Paul-mccartney",
    "iq": 1800
   },
   "artist": "Paul McCartney",
   "lyrics": "Ebony And Ivory live together in perfect harmony\nSide by side on my piano keyboard oh lord why dont we?\n\nWe all know that people are the same where ever you go\nThere is good and bad in everyone\nWe learn to live we learn to give each other what we need to survive together alive\n\nEbony and Ivory live together in perfect harmony\nSide by side on my piano keybard oh lord why dont we?\n\nEbony, Ivory living in pefect harmony\nEbony, Ivory oh..\n\nWe all know that people are the same where ever you go\nThere is good and bad in everyone\nWe learn to live when we learn to give each other what we need to survive\nTogether alive"
  }
 ]
}